[
  {
    "title": "dev",
    "multisNames": ["1_dev", "1_developer"],
    "subreddits": [
      "reactnative",
      "css",
      "Hosting",
      "learnwebdev",
      "web_design",
      "PostgreSQL",
      "Firebase",
      "webhosting",
      "learncss",
      "node",
      "reactjs",
      "learnjavascript",
      "Heroku",
      "learnreactjs",
      "vscode",
      "graphql",
      "jira",
      "Frontend",
      "gatsbyjs",
      "javascript",
      "webdev",
      "jquery",
      "learnprogramming",
      "cs50",
      "Meteor",
      "learndesign",
      "indesign",
      "Design",
      "learnwebdesign",
      "Database",
      "FlutterDev",
      "babeljs",
      "ITCareerQuestions",
      "scrum",
      "HTML",
      "graphic_design",
      "Domaining",
      "d3js",
      "compsci",
      "softwaredevelopment",
      "UXDesign",
      "BuildingWithJS",
      "learnandroid",
      "mobilewebdev",
      "ruby",
      "coding",
      "opensourcesociety",
      "programming",
      "PWA",
      "computerscience",
      "cscareerquestions",
      "resumes",
      "git",
      "softwarearchitecture",
      "agile",
      "html5",
      "C_Programming"
    ]
  },
  {
    "title": "business",
    "multisNames": ["0_business", "0_entrepreneur", "1_marketing"],
    "subreddits": [
      "businessschool",
      "economy",
      "Realestatefinance",
      "StockMarket",
      "passive_income",
      "almosthomeless",
      "venturecapital",
      "investing",
      "Patents",
      "Aquaculture",
      "BusinessHub",
      "InvestmentEducation",
      "realestateinvesting",
      "RealEstateTechnology",
      "Frugal",
      "StockNews",
      "InvestmentClub",
      "sales",
      "RealEstate",
      "RobinHood",
      "finance",
      "stocks",
      "Forex",
      "realtors",
      "franchise",
      "Real_Estate",
      "SecurityAnalysis",
      "Economics",
      "financialindependence",
      "Landlord",
      "MoneyHelp",
      "jobs",
      "Franchising",
      "povertyfinance",
      "AskEconomics",
      "Stock_Picks",
      "personalfinance",
      "leanfire",
      "GAMETHEORY",
      "FinancialPlanning",
      "business",
      "fatFIRE",
      "RealTop1Percent",
      "Business_Ideas",
      "growmybusiness",
      "freelance",
      "juststart",
      "roastmystartup",
      "SomebodyMakeThis",
      "SideProject",
      "MachineThatMakesMoney",
      "smallbusiness",
      "restaurateur",
      "pleenq",
      "ecommerce",
      "TeamItUp",
      "advancedentrepreneur",
      "AmazonFBATips",
      "Entrepreneur",
      "EntrepreneurRideAlong",
      "Startup_Ideas",
      "dailymarketing",
      "AppBusiness",
      "hwstartups",
      "eResidency",
      "startups",
      "BarOwners",
      "indiebiz",
      "IWantOut",
      "sweatystartup",
      "agency",
      "growthhacker",
      "advertising",
      "digitalfunnel",
      "DotCom",
      "AskMarketing",
      "InstagramMarketing",
      "GrowthHackingLabs",
      "GrowthHacking",
      "GrowthHack",
      "content_marketing",
      "Affiliatemarketing",
      "bigseo",
      "marketing",
      "Emailmarketing",
      "SEO",
      "analytics",
      "socialmediaanalytics",
      "GrowthHackerTips",
      "copywriting",
      "PPC",
      "Growth_Hacking",
      "webmarketing",
      "socialmedia"
    ]
  },
  {
    "title": "life",
    "multisNames": ["2_cook", "2_life"],
    "subreddits": [
      "fitmeals",
      "Cheap_Meals",
      "EatCheapAndHealthy",
      "gainit",
      "budgetfood",
      "studentfood",
      "foodhacks",
      "gainitmeals",
      "Cooking",
      "GettingShredded",
      "frugalmalefashion",
      "selfimprovement",
      "solotravel",
      "SocialEngineering",
      "tressless",
      "howtonotgiveafuck",
      "Life",
      "NoFap",
      "GetStudying",
      "askseddit",
      "malefashionadvice",
      "DecidingToBeBetter",
      "AmateurRoomPorn",
      "homegym",
      "lifelonglearning",
      "tipoftheday",
      "Fitness",
      "WatchHorology",
      "bodyweightfitness",
      "confidence",
      "productivity",
      "malelivingspace",
      "fragrance",
      "everymanshouldknow",
      "Posture",
      "LifeImprovement",
      "Semenretention",
      "malelifestyle",
      "ScandinavianInterior",
      "socialskills",
      "cycling",
      "ZenHabits",
      "HaircareScience",
      "weightroom",
      "InteriorDesign",
      "getdisciplined",
      "seduction",
      "MGTOW"
    ]
  }
]
